MANIFEST.in
README.rst
setup.py
robgracli/__init__.py
robgracli/client.py
robgracli/exceptions.py
robgracli/http.py
robgracli/tests/__init__.py
robgracli/tests/test_client.py
robust_graphite_client.egg-info/PKG-INFO
robust_graphite_client.egg-info/SOURCES.txt
robust_graphite_client.egg-info/dependency_links.txt
robust_graphite_client.egg-info/not-zip-safe
robust_graphite_client.egg-info/pbr.json
robust_graphite_client.egg-info/requires.txt
robust_graphite_client.egg-info/top_level.txt