Metadata-Version: 1.0
Name: robust-graphite-client
Version: 1.1.0
Summary: A simple graphite querying library with workarounds on some rare bugs
Home-page: https://github.com/Stupeflix/robust-graphite-client
Author: Luper Rouch
Author-email: luper.rouch@gmail.com
License: MIT
Platform: UNKNOWN
